deprl/__init__.py
deprl/custom_agents.py
deprl/custom_distributed.py
deprl/custom_mpo_torch.py
deprl/custom_replay_buffers/__init__.py
deprl/custom_replay_buffers/action_cost_replay.py
deprl/custom_test_environment.py
deprl/custom_torso.py
deprl/custom_trainer.py
deprl/dep_controller.py
deprl/env_wrappers/__init__.py
deprl/env_wrappers/dm_wrapper.py
deprl/env_wrappers/gym_wrapper.py
deprl/env_wrappers/scone_wrapper.py
deprl/env_wrappers/wrappers.py
deprl/log.py
deprl/main.py
deprl/param_files/default_agents.json
deprl/play.py
deprl/plot.py
deprl/utils/__init__.py
deprl/utils/load_utils.py
deprl/utils/utils.py
deprl/vendor/__init__.py
deprl/vendor/tonic/.gitignore
deprl/vendor/tonic/LICENSE
deprl/vendor/tonic/__init__.py
deprl/vendor/tonic/agents/__init__.py
deprl/vendor/tonic/agents/agent.py
deprl/vendor/tonic/agents/basic.py
deprl/vendor/tonic/environments/__init__.py
deprl/vendor/tonic/environments/builders.py
deprl/vendor/tonic/environments/legacy_distributed.py
deprl/vendor/tonic/environments/wrappers.py
deprl/vendor/tonic/explorations/__init__.py
deprl/vendor/tonic/explorations/noisy.py
deprl/vendor/tonic/play.py
deprl/vendor/tonic/plot.py
deprl/vendor/tonic/replays/__init__.py
deprl/vendor/tonic/replays/buffers.py
deprl/vendor/tonic/replays/segments.py
deprl/vendor/tonic/replays/utils.py
deprl/vendor/tonic/tensorflow/__init__.py
deprl/vendor/tonic/tensorflow/agents/__init__.py
deprl/vendor/tonic/tensorflow/agents/a2c.py
deprl/vendor/tonic/tensorflow/agents/agent.py
deprl/vendor/tonic/tensorflow/agents/d4pg.py
deprl/vendor/tonic/tensorflow/agents/ddpg.py
deprl/vendor/tonic/tensorflow/agents/mpo.py
deprl/vendor/tonic/tensorflow/agents/ppo.py
deprl/vendor/tonic/tensorflow/agents/sac.py
deprl/vendor/tonic/tensorflow/agents/td3.py
deprl/vendor/tonic/tensorflow/agents/td4.py
deprl/vendor/tonic/tensorflow/agents/trpo.py
deprl/vendor/tonic/tensorflow/models/__init__.py
deprl/vendor/tonic/tensorflow/models/actor_critics.py
deprl-0.5.0.dist-info/LICENSE
deprl-0.5.0.dist-info/METADATA
deprl-0.5.0.dist-info/WHEEL
deprl-0.5.0.dist-info/entry_points.txt
deprl-0.5.0.dist-info/RECORD
