Metadata-Version: 2.1
Name: deprl
Version: 0.5.0
Summary: DEP-RL, a method for robust control of musculoskeletal systems.
License: MIT
Author: Pierre Schumacher
Author-email: pierre.schumacher@tuebingen.mpg.de
Requires-Python: >=3.9,<=3.11.5
Classifier: License :: OSI Approved :: MIT License
Classifier: Programming Language :: Python :: 3
Classifier: Programming Language :: Python :: 3.9
Classifier: Programming Language :: Python :: 3.10
Classifier: Programming Language :: Python :: 3.11
Requires-Dist: gdown (>=5.1.0,<6.0.0)
Requires-Dist: gymnasium
Requires-Dist: numpy (>=1.22.4,<2.0.0)
Requires-Dist: pandas (>=2.0.1,<3.0.0)
Requires-Dist: pyyaml (>=6.0,<7.0)
Requires-Dist: termcolor (>=2.2.0,<3.0.0)
Requires-Dist: torch (>=2.1.0)
Requires-Dist: wandb (>=0.15.4,<0.16.0)
